avendesora/__init__.py
avendesora/account.py
avendesora/browsers.py
avendesora/charsets.py
avendesora/collection.py
avendesora/command.py
avendesora/config.py
avendesora/cursor.py
avendesora/dialog.py
avendesora/dictionary.py
avendesora/editors.py
avendesora/error.py
avendesora/file.py
avendesora/files.py
avendesora/generator.py
avendesora/gpg.py
avendesora/help.py
avendesora/main.py
avendesora/obscure.py
avendesora/otp.py
avendesora/preferences.py
avendesora/recognize.py
avendesora/script.py
avendesora/secrets.py
avendesora/shlib.py
avendesora/title.py
avendesora/utilities.py
avendesora/writer.py
avendesora-1.26.dist-info/entry_points.txt
avendesora-1.26.dist-info/WHEEL
avendesora-1.26.dist-info/METADATA
avendesora-1.26.dist-info/RECORD
