Metadata-Version: 2.1
Name: avendesora
Version: 1.26
Summary: A password generator and account manager.
Keywords: avendesora,password,password vault,XKCD
Author: Ken Kundert
Author-email: avendesora@nurdletech.com
Requires-Python: >=3.6
Classifier: Development Status :: 5 - Production/Stable
Classifier: Environment :: Console
Classifier: Intended Audience :: End Users/Desktop
Classifier: License :: OSI Approved :: GNU General Public License v3 or later (GPLv3+)
Classifier: Natural Language :: English
Classifier: Operating System :: POSIX :: Linux
Classifier: Programming Language :: Python :: 3
Classifier: Topic :: Security :: Cryptography
Classifier: Topic :: Utilities
Requires-Dist: appdirs
Requires-Dist: arrow!=0.14.*
Requires-Dist: cryptography
Requires-Dist: docopt
Requires-Dist: inform
Requires-Dist: pygobject
Requires-Dist: python-gnupg>=0.4.4
Requires-Dist: pyotp
Project-URL: changelog, https://avendesora.readthedocs.io/en/latest/releases.html
Project-URL: documentation, https://avendesora.readthedocs.io
Project-URL: homepage, https://avendesora.readthedocs.io
Project-URL: repository, https://github.com/kenkundert/avendesora
